eaps2000.py
eaps2000-1.1.1.dist-info/METADATA
eaps2000-1.1.1.dist-info/WHEEL
eaps2000-1.1.1.dist-info/entry_points.txt
eaps2000-1.1.1.dist-info/RECORD
