Metadata-Version: 2.4
Name: eaps2000
Version: 1.1.1
Summary: Elektro-Automatik Series PS 2000 Python Controller
Project-URL: Homepage, https://github.com/KozhinovAlexander/eaps2000
Project-URL: Documentation, https://github.com/KozhinovAlexander/eaps2000/blob/main/README.md
Author-email: Alexander Kozhinov <ak.alexander.kozhinov@gmail.com>
License-Expression: Apache-2.0
Keywords: ds-power-supply,ea-ps-2042-06b,ea-ps-2042-10b,ea-ps-2042-20b,ea-ps-2084-03b,ea-ps-2084-05b,ea-ps-2342-06b,ea-ps-2342-10b,ea-ps-2384-05b,psu,psu-controller,pypi-package,python-psu-controller,series-ps-2000-b
Classifier: Development Status :: 5 - Production/Stable
Classifier: Programming Language :: Python
Requires-Python: >=3.8
Requires-Dist: pyserial>=3.5
Provides-Extra: dev
Requires-Dist: flake8>=7.1.2; extra == 'dev'
Requires-Dist: pytest-flake8>=1.3.0; extra == 'dev'
Requires-Dist: pytest>=6.2.2; extra == 'dev'
Requires-Dist: versioningit>=3.1.2; extra == 'dev'
